my_pkg/__init__.py
my_pkg/my_module.py
my_pkg_binlecode-0.1.3.dist-info/METADATA
my_pkg_binlecode-0.1.3.dist-info/WHEEL
my_pkg_binlecode-0.1.3.dist-info/top_level.txt
my_pkg_binlecode-0.1.3.dist-info/RECORD
