Metadata-Version: 2.1
Name: my-pkg-binlecode
Version: 0.1.3
Summary: A small test package by setuptools
Home-page: https://github.com/binlecode/example-python-setuptools
Author: Bin Le
Author-email: Bin Le <bin.le.code@gmail.com>
License: MIT
Project-URL: Homepage, https://github.com/binlecode/example-python-setuptools
Classifier: Programming Language :: Python :: 3
Classifier: Topic :: Software Development
Requires-Python: >=3.8
Provides-Extra: dev
Requires-Dist: black ; extra == 'dev'
